_trio_parallel_workers/__init__.py
_trio_parallel_workers/_funcs.py
trio_parallel/__init__.py
trio_parallel/_abc.py
trio_parallel/_impl.py
trio_parallel/_posix_pipes.py
trio_parallel/_proc.py
trio_parallel/_windows_cffi.py
trio_parallel/_windows_pipes.py
trio_parallel/_tests/__init__.py
trio_parallel/_tests/conftest.py
trio_parallel/_tests/test_cache.py
trio_parallel/_tests/test_defaults.py
trio_parallel/_tests/test_impl.py
trio_parallel/_tests/test_proc.py
trio_parallel/_tests/test_worker.py
trio_parallel-1.3.0.dist-info/LICENSE
trio_parallel-1.3.0.dist-info/LICENSE.APACHE2
trio_parallel-1.3.0.dist-info/LICENSE.MIT
trio_parallel-1.3.0.dist-info/METADATA
trio_parallel-1.3.0.dist-info/WHEEL
trio_parallel-1.3.0.dist-info/top_level.txt
trio_parallel-1.3.0.dist-info/RECORD
