Metadata-Version: 2.1
Name: trio-parallel
Version: 1.3.0
Summary: CPU parallelism for Trio
Author-email: Richard Sheridan <richard.sheridan@gmail.com>
License: MIT OR Apache-2.0
Project-URL: Homepage, https://github.com/richardsheridan/trio-parallel
Project-URL: Documentation, https://trio-parallel.readthedocs.io/
Project-URL: Changelog, https://trio-parallel.readthedocs.io/en/latest/history.html
Keywords: parallel,trio,async,dispatch,multiprocessing
Classifier: License :: OSI Approved :: MIT License
Classifier: License :: OSI Approved :: Apache Software License
Classifier: Framework :: Trio
Classifier: Operating System :: POSIX :: Linux
Classifier: Operating System :: MacOS :: MacOS X
Classifier: Operating System :: Microsoft :: Windows
Classifier: Programming Language :: Python :: 3 :: Only
Classifier: Programming Language :: Python :: 3.9
Classifier: Programming Language :: Python :: 3.10
Classifier: Programming Language :: Python :: 3.11
Classifier: Programming Language :: Python :: 3.12
Classifier: Programming Language :: Python :: 3.13
Classifier: Programming Language :: Python :: Implementation :: CPython
Classifier: Programming Language :: Python :: Implementation :: PyPy
Classifier: Development Status :: 5 - Production/Stable
Classifier: Intended Audience :: Developers
Classifier: Intended Audience :: Financial and Insurance Industry
Classifier: Intended Audience :: Science/Research
Classifier: Topic :: Software Development :: Libraries
Requires-Python: >=3.7
License-File: LICENSE
License-File: LICENSE.APACHE2
License-File: LICENSE.MIT
Requires-Dist: trio>=0.18.0
Requires-Dist: outcome
Requires-Dist: attrs>=17.3.0
Requires-Dist: cffi; os_name == "nt" and implementation_name != "pypy"
Requires-Dist: tblib
Requires-Dist: tricycle>=0.3.0
Provides-Extra: test
Requires-Dist: pytest; extra == "test"
Requires-Dist: pytest-trio; extra == "test"
Requires-Dist: trio>=0.23.0; extra == "test"
